rough/__init__.py
rough/approximation.py
rough/decisions.py
rough/granulation.py
rough/operations.py
rough/utils.py
rough_theory-0.0.3.dist-info/METADATA
rough_theory-0.0.3.dist-info/WHEEL
rough_theory-0.0.3.dist-info/licenses/LICENSE
rough_theory-0.0.3.dist-info/RECORD
